morm/__init__.py
morm/orm.py
morm/utils.py
morm_python-0.2.3.dist-info/LICENSE
morm_python-0.2.3.dist-info/METADATA
morm_python-0.2.3.dist-info/WHEEL
morm_python-0.2.3.dist-info/RECORD
