Metadata-Version: 2.3
Name: morm-python
Version: 0.2.3
Summary: Asynchronous Mongo ORM
License: MIT
Author: MrNereof
Author-email: mrnereof@gmail.com
Requires-Python: >=3.11,<4.0
Classifier: License :: OSI Approved :: MIT License
Classifier: Programming Language :: Python :: 3
Classifier: Programming Language :: Python :: 3.11
Classifier: Programming Language :: Python :: 3.12
Classifier: Programming Language :: Python :: 3.13
Requires-Dist: pydantic (>=2.4.1,<3.0.0)
Requires-Dist: pymongo (>=4.13.0,<5.0.0)
